einml/__init__.py
einml/export.py
einml/metrics.py
einml/prelude.py
einml/progress.py
einml/run_name.py
einml/tf_types.py
einml/train.py
einml/utils.py
einml-0.1.1.dist-info/METADATA
einml-0.1.1.dist-info/WHEEL
einml-0.1.1.dist-info/RECORD
